{
  "Overall": [
    {
      "graphName": "Points scored",
      "metrics": [
        {
          "path": "$['03auto'].autofuel",
          "weight": 1
        },
        {
          "path": "$['04teleop'].teleFuel",
          "weight": 1
        },
        {
          "path": "$['03auto'].autoClimb",
          "weight": 15
        },
        {
          "path": "$['05endgame'][?(@.name == 'L1')]",
          "weight": 10
        },
        {
          "path": "$['05endgame'][?(@.name == 'L2')]",
          "weight": 20
        },
        {
          "path": "$['05endgame'][?(@.name == 'L3')]",
          "weight": 30
        }
        
      ],
      "units": "Points"
    },
    {
      "graphName": "Fuel Scored",
      "metrics": [
        { "path": "$['03auto'].autofuel", "weight": 1 },
        { "path": "$['04teleop'].teleFuel", "weight": 1 }
      ],
      "units": "Fuel"
    },
    {
      "graphName": "Climb Points",
      "metrics": [
       {
          "path": "$.autoClimb",
          "weight": 15
        },
        {
          "path": "$['05endgame'][?(@.name == 'L1')]",
          "weight": 10
        },
        {
          "path": "$['05endgame'][?(@.name == 'L2')]",
          "weight": 20
        },
        {
          "path": "$['05endgame'][?(@.name == 'L3')]",
          "weight": 30
        }
      ],
      "units": "Points"
    },
    {
      "graphName": "Defense",
      "metrics":[
        {
          "path":"$['06extra'].defense",
          "weight":1  
        }
      ],
      "units": "Rating"
    },
    {
      "graphName": "Impact when Defended",
      "metrics":[
        {
          "path":"$['06extra'].defended",
          "weight":1  
        }
      ],
      "units": "Rating"
    },
    {
      "graphName": "Ferrying",
      "metrics":[
        {
          "path":"$['06extra'].ferry",
          "weight":1  
        }
      ],
      "units": "Rating"
    }


  ],
  "Teleop": [
    {
      "graphName": "Points scored",
      "metrics": [{
          "path": "$['04teleop'].teleFuel",
          "weight": 1
        },

                {
          "path": "$['04teleop'][?(@.result == 'Score 5')]",
          "weight": 5
        },
        {
          "path": "$['04teleop'][?(@.result == 'Score 3')]",
          "weight": 3
        },
        {
          "path": "$['04teleop'][?(@.result == 'Score 1')]",
          "weight": 1
        },
        {
          "path": "$['05endgame'][?(@.name == 'L1')]",
          "weight": 10
        },
        {
          "path": "$['05endgame'][?(@.name == 'L2')]",
          "weight": 20
        },
        {
          "path": "$['05endgame'][?(@.name == 'L3')]",
          "weight": 30
        }
      ],
      "units": "Points"
    },
    {
      "graphName":"Fuel Scored",
      "metrics":[
        { "path": "$.telefuel", "weight": 1 },
        {
          "path": "$['04teleop'][?(@.result == 'Score 5')]",
          "weight": 5
        },
        {
          "path": "$['04teleop'][?(@.result == 'Score 3')]",
          "weight": 3
        },
        {
          "path": "$['04teleop'][?(@.result == 'Score 1')]",
          "weight": 1
        },
        {
          "path": "$['04teleop'].teleFuel",
          "weight": 1
        }
      ],
      "units": "Fuel"
    }
    
  ],
  "Auto": [
    {
      "graphName": "Points scored",
      "metrics": [
        {
          "path": "$['03auto'].autofuel",
          "weight": 1
        },
        {
          "path": "$['03auto'].autoClimb",
          "weight": 15
        }
      ],
      "units": "Points"
    },
    {
      "graphName": "Fuel scored",
      "metrics": [
        {
          "path": "$['03auto'].autoFuel",
          "weight":1
        }
      ],
      "units": "Fuel"
    },
    {
      "graphName": "Climb",
      "metrics":[
        { "path": "$['03auto'].autoClimb", "weight":15}
      ]
    }
    
  ],
  "Endgame": [
    {
      "graphName": "Total Climb Points",
      "metrics": [
        { "path": "$['03auto'].autoClimb", "weight":15},
        { "path": "$['05endgame'][?(@.name == 'L1')]", "weight":10},
        { "path": "$['05endgame'][?(@.name == 'L2')]", "weight":20},
        { "path": "$['05endgame'][?(@.name == 'L3')]", "weight":30}
      ],
      "units": "Points"
    }
  ],
  "Driver": [
    {
      "graphName": "Quality",
      "metrics": [
        {
          "path": "$[?(@.Driver_Quality== 'Bad')]",
           "weight": 1
        },
        {
          "path": "$[?(@.Driver_Quality== 'Average')]",
          "weight": 2
        },
        {
          "path":"$[?(@.Driver_Quality== 'Good')]",
          "weight":3
        }
      ],
      "units": "Quality"
    }
  ],
  "Comparison": [
    {
      "graphName": "Fuel Scored",
      "metrics": [
        { "path": "$['03auto'].autofuel", "weight": 1 },
        { "path": "$['04teleop'].telefuel", "weight": 1 }
      ],
      "units": "Pieces"
    },
    {
      "graphName": "Points scored",
      "metrics": [
       {
          "path": "$['03auto'].autofuel",
          "weight": 1
        },
        {
          "path": "$['04teleop'].teleFuel",
          "weight": 1
        },
        {
          "path": "$['03auto'].autoClimb",
          "weight": 15
        },
        {
          "path": "$['05endgame'][?(@.name == 'L1')]",
          "weight": 10
        },
        {
          "path": "$['05endgame'][?(@.name == 'L2')]",
          "weight": 20
        },
        {
          "path": "$['05endgame'][?(@.name == 'L3')]",
          "weight": 30
        }

      ],
      "units": "Points"
    }
  ]
}
