{
  "Overall": [
    {
      "graphName": "Points scored",
      "metrics": [
        { "path": "$['03auto'][?(@.result == 'Score 1')]", "weight": 1 },
        { "path": "$['03auto'][?(@.result == 'Score 3')]", "weight": 3 },
        {
          "path": "$['03auto'][?(@.result == 'Score 5')]",
          "weight": 5
        },
        {
          "path": "$['04teleop'][?(@.result == 'Score 5')]",
          "weight": 5
        },
        {
          "path": "$['04teleop'][?(@.result == 'Score 3')]",
          "weight": 3
        },
        {
          "path": "$['04teleop'][?(@.result == 'Score 1')]",
          "weight": 1
        },
        {
          "path": "$['03auto'].autoFuel",
          "weight": 1
        },
        {
          "path": "$['04teleop'].teleFuel",
          "weight": 1
        },
        {
          "path": "$['03auto'].autoClimb",
          "weight": 15
        },
        {
          "path": "$['05endgame'][?(@.name == 'L1')]",
          "weight": 10
        },
        {
          "path": "$['05endgame'][?(@.name == 'L2')]",
          "weight": 20
        },
        {
          "path": "$['05endgame'][?(@.name == 'L3')]",
          "weight": 30
        }
        
      ],
      "units": "Points"
    },
    {
      "graphName": "Fuel Scored",
      "metrics": [
        { "path": "$['03auto'][?(@.result == 'Score 5')]", "weight": 5 },
        { "path": "$['04teleop'][?(@.result == 'Score 5')]", "weight": 5 },
        { "path": "$['03auto'][?(@.result == 'Score 3')]", "weight": 3 },
        { "path": "$['04teleop'][?(@.result == 'Score 3')]", "weight": 3 } ,
        { "path": "$['03auto'][?(@.result == 'Score 1')]", "weight": 1 },
        { "path": "$['04teleop'][?(@.result == 'Score 1')]", "weight": 1 },
        { "path": "$['03auto'][?(@.result == 'Ferry 5')]", "weight": 5 },
        { "path": "$['04teleop'][?(@.result == 'Ferry 5')]", "weight": 5 },
        { "path": "$['03auto'][?(@.result == 'Ferry 3')]", "weight": 3 },
        { "path": "$['04teleop'][?(@.result == 'Ferry 3')]", "weight": 3 } ,
        { "path": "$['03auto'][?(@.result == 'Ferry 1')]", "weight": 1 },
        { "path": "$['04teleop'][?(@.result == 'Ferry 1')]", "weight": 1 },
        { "path": "$['03auto'].autofuel", "weight": 1 },
        { "path": "$['04teleop'].teleFuel", "weight": 1 }

        
      ],
      "units": "Fuel"
    },
    {
      "graphName": "Climb Points",
      "metrics": [
       {
          "path": "$.autoClimb",
          "weight": 15
        },
        {
          "path": "$['05endgame'][?(@.name == 'L1')]",
          "weight": 10
        },
        {
          "path": "$['05endgame'][?(@.name == 'L2')]",
          "weight": 20
        },
        {
          "path": "$['05endgame'][?(@.name == 'L3')]",
          "weight": 30
        }
      ],
      "units": "Points"
    }
  ],
  "Teleop": [
    {
      "graphName": "Points scored",
      "metrics": [{
          "path": "$['04teleop'].teleFuel",
          "weight": 1
        },
                {
          "path": "$['04teleop'][?(@.result == 'Score 5')]",
          "weight": 5
        },
        {
          "path": "$['04teleop'][?(@.result == 'Score 3')]",
          "weight": 3
        },
        {
          "path": "$['04teleop'][?(@.result == 'Score 1')]",
          "weight": 1
        },
        {
          "path": "$['05endgame'][?(@.name == 'L1')]",
          "weight": 10
        },
        {
          "path": "$['05endgame'][?(@.name == 'L2')]",
          "weight": 20
        },
        {
          "path": "$['05endgame'][?(@.name == 'L3')]",
          "weight": 30
        }
      ],
      "units": "Points"
    },
    {
      "graphName":"Fuel Scored",
      "metrics":[
        { "path": "$.telefuel", "weight": 1 },
        {
          "path": "$['04teleop'][?(@.result == 'Score 5')]",
          "weight": 5
        },
        {
          "path": "$['04teleop'][?(@.result == 'Score 3')]",
          "weight": 3
        },
        {
          "path": "$['04teleop'][?(@.result == 'Score 1')]",
          "weight": 1
        },
        {
          "path": "$['04teleop'].teleFuel",
          "weight": 1
        }
      ],
      "units": "Fuel"
    },
    {
      "graphName": "Fuel Ferried",
      "metrics": [
        {
          "path": "$['04teleop'][?(@.result == 'Ferry 5')]",
          "weight": 5
        },
        {
          "path": "$['04teleop'][?(@.result == 'Ferry 3')]",
          "weight": 3
        },
        {
          "path": "$['04teleop'][?(@.result == 'Ferry 1')]",
          "weight": 1
        },
                {
          "path": "$['04teleop'][?(@.result == 'Ferry Long 5')]",
          "weight": 5
        },
        {
          "path": "$['04teleop'][?(@.result == 'Ferry Long 3')]",
          "weight": 3
        },
        {
          "path": "$['04teleop'][?(@.result == 'Ferry Long 1')]",
          "weight": 1
        }
      ],
      "units": "Points"
    }
    
  ],
  "Auto": [
    {
      "graphName": "Points scored",
      "metrics": [
        {
          "path": "$.autofuel",
          "weight": 1
        },
        {
          "path": "$.autoclimb",
          "weight": 15
        }
      ],
      "units": "Points"
    },
    {
      "graphName": "Fuel scored",
      "metrics": [
        {
          "path": "$.autofuel",
          "weight":1
        }
      ],
      "units": "Fuel"
    },
    {
      "graphName": "Climb",
      "metrics":[
        { "path": "$.autoclimb", "weight":15},
        { "path": "$[?(@.autoclimb == 1)]", "weight":4}
      ]
    }
    
  ],
  "Endgame": [
    {
      "graphName": "Total Climb Points",
      "metrics": [
        { "path": "$.autoclimb", "weight":15},
        { "path": "$.endclimbposition", "weight":10}
      ],
      "units": "Points"
    },
    {
      "graphName": "Failed Auto Climbs",
      "metrics": [
        { "path": "$[?(@.autoclimb == 1)]", "weight":1}
      ],
      "units": "Climbs"
    }
  ],
  "Driver": [
    {
      "graphName": "Quality",
      "metrics": [
        {
          "path": "$[?(@.Driver_Quality== 'Bad')]",
           "weight": 1
        },
        {
          "path": "$[?(@.Driver_Quality== 'Average')]",
          "weight": 2
        },
        {
          "path":"$[?(@.Driver_Quality== 'Good')]",
          "weight":3
        }
      ],
      "units": "Quality"
    }
  ],
  "Comparison": [
    {
      "graphName": "Fuel Scored",
      "metrics": [
        { "path": "$['03auto'][?(@.result == 'Score 5')]", "weight": 5 },
        { "path": "$['04teleop'][?(@.result == 'Score 5')]", "weight": 5 },
        { "path": "$['03auto'][?(@.result == 'Score 3')]", "weight": 3 },
        { "path": "$['04teleop'][?(@.result == 'Score 3')]", "weight": 3 } ,
        { "path": "$['03auto'][?(@.result == 'Score 1')]", "weight": 1 },
        { "path": "$['04teleop'][?(@.result == 'Score 1')]", "weight": 1 },
        { "path": "$['03auto'][?(@.result == 'Ferry 5')]", "weight": 5 },
        { "path": "$['04teleop'][?(@.result == 'Ferry 5')]", "weight": 5 },
        { "path": "$['03auto'][?(@.result == 'Ferry 3')]", "weight": 3 },
        { "path": "$['04teleop'][?(@.result == 'Ferry 3')]", "weight": 3 } ,
        { "path": "$['03auto'][?(@.result == 'Ferry 1')]", "weight": 1 },
        { "path": "$['04teleop'][?(@.result == 'Ferry 1')]", "weight": 1 },
        { "path": "$.autofuel", "weight": 1 },
        { "path": "$.telefuel", "weight": 1 }
      ],
      "units": "Pieces"
    },
    {
      "graphName": "Points scored",
      "metrics": [
               { "path": "$['03auto'][?(@.result == 'Score 1')]", "weight": 1 },
        { "path": "$['03auto'][?(@.result == 'Score 3')]", "weight": 3 },
        {
          "path": "$['03auto'][?(@.result == 'Score 5')]",
          "weight": 5
        },
        {
          "path": "$['04teleop'][?(@.result == 'Score 5')]",
          "weight": 5
        },
        {
          "path": "$['04teleop'][?(@.result == 'Score 3')]",
          "weight": 3
        },
        {
          "path": "$['04teleop'][?(@.result == 'Score 1')]",
          "weight": 1
        },
        {
          "path": "$.autofuel",
          "weight": 1
        },
        {
          "path": "$.telefuel",
          "weight": 1
        },
        {"path": "$.autoclimb","weight": 15},
        {"path": "$.endclimbposition","weight": 10}

      ],
      "units": "Points"
    }
  ]
}
